ntscraper/__init__.py
ntscraper/nitter.py
ntscraper-0.4.0.dist-info/LICENSE.txt
ntscraper-0.4.0.dist-info/METADATA
ntscraper-0.4.0.dist-info/WHEEL
ntscraper-0.4.0.dist-info/top_level.txt
ntscraper-0.4.0.dist-info/RECORD
