Metadata-Version: 2.1
Name: ntscraper
Version: 0.4.0
Summary: Unofficial library to scrape Twitter profiles and posts from Nitter instances
Author: Lorenzo Bocchi
Author-email: lorenzobocchi99@yahoo.com
License: MIT
Project-URL: Homepage, https://github.com/bocchilorenzo/ntscraper
Project-URL: Source, https://github.com/bocchilorenzo/ntscraper
Project-URL: Documentation, https://github.com/bocchilorenzo/ntscraper
Keywords: twitter,nitter,scraping
Classifier: Intended Audience :: Developers
Classifier: License :: OSI Approved :: MIT License
Classifier: Programming Language :: Python
Classifier: Programming Language :: Python :: 3
Classifier: Programming Language :: Python :: 3.7
Classifier: Programming Language :: Python :: 3.9
Classifier: Programming Language :: Python :: 3.10
Classifier: Operating System :: OS Independent
License-File: LICENSE.txt
Requires-Dist: requests (>=2.28)
Requires-Dist: beautifulsoup4 (>=4.11)
Requires-Dist: lxml (>=4.9)
Requires-Dist: tqdm (>=4.66)
